MANIFEST.in
README.md
setup.py
TOPSIS_Kartik_101803696.egg-info/PKG-INFO
TOPSIS_Kartik_101803696.egg-info/SOURCES.txt
TOPSIS_Kartik_101803696.egg-info/dependency_links.txt
TOPSIS_Kartik_101803696.egg-info/requires.txt
TOPSIS_Kartik_101803696.egg-info/top_level.txt
Topsis_Kartik_101803696/TOPSIS-Kartik-101803696.py