Metadata-Version: 2.1
Name: TOPSIS-Kartik-101803696
Version: 1.0.1
Summary: A Python package to get best out of various features using TOPSIS.
Home-page: https://github.com/Kartik-Bhardwaj192/topsis
Author: Kartik Bhardwaj
Author-email: kbhardwaj_be18@thapar.edu
License: MIT
Platform: UNKNOWN
Classifier: License :: OSI Approved :: MIT License
Classifier: Programming Language :: Python :: 3
Classifier: Programming Language :: Python :: 3.7
Classifier: Programming Language :: Python :: 3.6
